bareml/__init__.py
bareml/deeplearning/__init__.py
bareml/deeplearning/config.py
bareml/deeplearning/core.py
bareml/deeplearning/cuda.py
bareml/deeplearning/data.py
bareml/deeplearning/functions.py
bareml/deeplearning/layers.py
bareml/deeplearning/metrics.py
bareml/deeplearning/models.py
bareml/deeplearning/optimisers.py
bareml/deeplearning/transforms.py
bareml/deeplearning/utils.py
bareml/machinelearning/__init__.py
bareml/machinelearning/base.py
bareml/machinelearning/wrappers.py
bareml/machinelearning/ensemble/__init__.py
bareml/machinelearning/ensemble/adaboost.py
bareml/machinelearning/ensemble/baggings.py
bareml/machinelearning/ensemble/gradient_boosting.py
bareml/machinelearning/ensemble/stacking.py
bareml/machinelearning/ensemble/voting.py
bareml/machinelearning/ensemble/xgboost.py
bareml/machinelearning/supervised/__init__.py
bareml/machinelearning/supervised/decision_trees.py
bareml/machinelearning/supervised/kernel_regression.py
bareml/machinelearning/supervised/knn.py
bareml/machinelearning/supervised/linear_regression.py
bareml/machinelearning/supervised/logistic_regression.py
bareml/machinelearning/supervised/naive_bayes.py
bareml/machinelearning/supervised/perceptron.py
bareml/machinelearning/unsupervised/__init__.py
bareml/machinelearning/unsupervised/dbscan.py
bareml/machinelearning/unsupervised/kmeans.py
bareml/machinelearning/utils/__init__.py
bareml/machinelearning/utils/kernels.py
bareml/machinelearning/utils/metrics.py
bareml/machinelearning/utils/misc.py
bareml/machinelearning/utils/model_selection.py
bareml/machinelearning/utils/optim.py
bareml/machinelearning/utils/preprocessing.py
bareml/machinelearning/utils/probabilities.py
bareml-0.0.9.dist-info/METADATA
bareml-0.0.9.dist-info/RECORD
bareml-0.0.9.dist-info/WHEEL
bareml-0.0.9.dist-info/top_level.txt
tests/__init__.py
tests/test_dbscan.py
tests/test_dl_functions.py
tests/test_dl_gradients.py
tests/test_kernel_regression.py
tests/test_kmeans.py
tests/test_knn.py
tests/test_linear_regression.py
tests/test_logistic_regression.py
tests/test_naive_bayes.py
