Metadata-Version: 2.1
Name: bareml
Version: 0.0.9
Summary: A Python module containing various machine learning algorithms.
Home-page: https://github.com/shotahorii/bareml
Author: shotahorii
Author-email: sh.sinker@gmail.com
License: MIT
Keywords: machine-learning machine-learning-algorithms machine-learning-from-scratch data-science statistical-models
Platform: UNKNOWN
Classifier: License :: OSI Approved :: MIT License
Classifier: Development Status :: 2 - Pre-Alpha
Classifier: Programming Language :: Python :: 3.7
Classifier: Programming Language :: Python :: 3.8
Requires-Dist: numpy
